Metadata-Version: 2.1
Name: WpaTestPackage
Version: 0.0.2
Summary: package for wpa test
Home-page: UNKNOWN
Author: Example Author
Author-email: pratikjadhao1965@example.com
License: UNKNOWN
Platform: UNKNOWN
Classifier: Programming Language :: Python :: 3
Classifier: License :: OSI Approved :: MIT License
Classifier: Operating System :: OS Independent
Requires-Python: >=3.6
